simulai/__init__.py
simulai/abstract.py
simulai/activations.py
simulai/batching.py
simulai/file.py
simulai/io.py
simulai/mesh.py
simulai/metrics.py
simulai/normalization.py
simulai/parallel.py
simulai/simulation.py
simulai/special.py
simulai/tokens.py
simulai/math/__init__.py
simulai/math/differentiation.py
simulai/math/expressions.py
simulai/math/filtering.py
simulai/math/integration.py
simulai/math/kansas.py
simulai/math/products.py
simulai/math/progression.py
simulai/math/quadratures.py
simulai/math/spaces.py
simulai/models/__init__.py
simulai/models/_models.py
simulai/models/_pytorch_models/__init__.py
simulai/models/_pytorch_models/_autoencoder.py
simulai/models/_pytorch_models/_deeponet.py
simulai/models/_pytorch_models/_miscellaneous.py
simulai/models/_pytorch_models/_nif.py
simulai/models/_pytorch_models/_transformer.py
simulai/models/_pytorch_models/_unet.py
simulai/optimization/__init__.py
simulai/optimization/_adjusters.py
simulai/optimization/_builtin.py
simulai/optimization/_builtin_pytorch.py
simulai/optimization/_losses.py
simulai/optimization/_optimization.py
simulai/regression/__init__.py
simulai/regression/_affine.py
simulai/regression/_elm.py
simulai/regression/_esn.py
simulai/regression/_extended_opinf.py
simulai/regression/_opinf.py
simulai/regression/_pinv.py
simulai/regression/_pytorch/__init__.py
simulai/regression/_pytorch/_conv.py
simulai/regression/_pytorch/_dense.py
simulai/regression/_pytorch/_koopman.py
simulai/regression/_pytorch/_numpy.py
simulai/regression/_pytorch/_opinf.py
simulai/regression/_pytorch/_rbf.py
simulai/residuals/__init__.py
simulai/residuals/_pytorch_residuals.py
simulai/rom/__init__.py
simulai/rom/_rom.py
simulai/sampling/__init__.py
simulai/sampling/_hamiltonian_sampling.py
simulai/templates/__init__.py
simulai/templates/_pytorch_network.py
simulai/templates/_templates.py
simulai/utilities/__init__.py
simulai/utilities/_makedirs_to_file.py
simulai/utilities/_tmp_dir.py
simulai/utilities/_visualization.py
simulai_toolkit-0.99.28.dist-info/AUTHORS.rst
simulai_toolkit-0.99.28.dist-info/LICENSE
simulai_toolkit-0.99.28.dist-info/METADATA
simulai_toolkit-0.99.28.dist-info/WHEEL
simulai_toolkit-0.99.28.dist-info/top_level.txt
simulai_toolkit-0.99.28.dist-info/RECORD
