Metadata-Version: 2.1
Name: simulai-toolkit
Version: 0.99.28
Summary: A Python package with data-driven pipelines for physics-informed machine learning
License: Apache License, Version 2.0
Project-URL: Source, https://github.com/IBM/simulai
Project-URL: Tracker, https://github.com/IBM/simulai/issues
Project-URL: Documentation, https://simulai-toolkit.readthedocs.io
Classifier: Development Status :: 4 - Beta
Classifier: Intended Audience :: Science/Research
Classifier: License :: OSI Approved :: Apache Software License
Classifier: Natural Language :: English
Classifier: Operating System :: OS Independent
Classifier: Programming Language :: Python :: 3.8
Classifier: Programming Language :: Python :: 3.9
Classifier: Programming Language :: Python :: Implementation :: CPython
Classifier: Topic :: Scientific/Engineering :: Physics
Classifier: Topic :: Scientific/Engineering :: Mathematics
Classifier: Topic :: Scientific/Engineering :: Artificial Intelligence
Classifier: Topic :: Software Development :: Libraries :: Python Modules
Requires-Python: >=3.8
License-File: LICENSE
License-File: AUTHORS.rst
Requires-Dist: numpy
Requires-Dist: numba
Requires-Dist: scipy <1.11.1
Requires-Dist: sympy
Requires-Dist: torch <=2.0.1
Requires-Dist: scikit-learn
Requires-Dist: psutil
Requires-Dist: h5py
Requires-Dist: dask
Requires-Dist: six
Requires-Dist: numexpr
Requires-Dist: minio
Requires-Dist: optuna
Requires-Dist: urllib3 <1.27
Provides-Extra: dev
Requires-Dist: yapf ; extra == 'dev'
Requires-Dist: bumpver ; extra == 'dev'
Requires-Dist: flake8 ; extra == 'dev'
Requires-Dist: coverage ; extra == 'dev'
Requires-Dist: pytest ; extra == 'dev'
Provides-Extra: mpi
Requires-Dist: mpi4py ; extra == 'mpi'
